graph_jsp_env/__init__.py
graph_jsp_env/disjunctive_graph_jsp_env.py
graph_jsp_env/disjunctive_graph_jsp_visualizer.py
graph_jsp_env/disjunctive_graph_logger.py
graph_jsp_env/py.typed
graph_jsp_env/wzl_ima_banner.py
graph_jsp_env-1.1.0.dist-info/licenses/LICENSE
graph_jsp_env-1.1.0.dist-info/METADATA
graph_jsp_env-1.1.0.dist-info/WHEEL
graph_jsp_env-1.1.0.dist-info/top_level.txt
graph_jsp_env-1.1.0.dist-info/RECORD
