Metadata-Version: 2.4
Name: graph-jsp-env
Version: 1.1.0
Summary: A flexible enviorment for job shop scheduling using the disjunctive graph apporach.
Author: Alexander Nasuta
Author-email: Alexander Nasuta <alexander.nasuta@ima.rwth-aachen.de>
License: MIT License
Project-URL: Homepage, https://github.com/Alexander-Nasuta/graph-jsp-env
Platform: unix
Platform: linux
Platform: osx
Platform: cygwin
Platform: win32
Classifier: License :: OSI Approved :: MIT License
Classifier: Programming Language :: Python
Classifier: Programming Language :: Python :: 3
Requires-Python: >=3.9
License-File: LICENSE
Requires-Dist: rich
Requires-Dist: opencv-python
Requires-Dist: plotly
Requires-Dist: networkx>=3
Requires-Dist: matplotlib
Requires-Dist: numpy
Requires-Dist: pandas
Requires-Dist: kaleido
Requires-Dist: gymnasium
Provides-Extra: dev
Requires-Dist: bumpver; extra == "dev"
Requires-Dist: pip-tools; extra == "dev"
Requires-Dist: pytest; extra == "dev"
Requires-Dist: pytest-cov; extra == "dev"
Requires-Dist: mypy; extra == "dev"
Requires-Dist: flake8; extra == "dev"
Requires-Dist: stable_baselines3; extra == "dev"
Requires-Dist: tox; extra == "dev"
Requires-Dist: sphinx; extra == "dev"
Requires-Dist: myst-parser; extra == "dev"
Requires-Dist: sphinx-autobuild; extra == "dev"
Requires-Dist: furo; extra == "dev"
Requires-Dist: twine; extra == "dev"
Requires-Dist: sphinx-copybutton; extra == "dev"
Requires-Dist: sphinxcontrib-bibtex; extra == "dev"
Requires-Dist: sphinxcontrib.tikz; extra == "dev"
Requires-Dist: sphinxcontrib-jsmath; extra == "dev"
Requires-Dist: nbsphinx; extra == "dev"
Requires-Dist: sb3_contrib; extra == "dev"
Requires-Dist: jupytext; extra == "dev"
Requires-Dist: notebook; extra == "dev"
Requires-Dist: typing_extensions>=4.12.0; extra == "dev"
Dynamic: license-file
